excel2flapjack/__init__.py
excel2flapjack/main.py
excel2flapjack-1.0.11.dist-info/METADATA
excel2flapjack-1.0.11.dist-info/WHEEL
excel2flapjack-1.0.11.dist-info/top_level.txt
excel2flapjack-1.0.11.dist-info/RECORD
